LICENSE
README.rst
setup.py
msig/MSig.py
msig/__init__.py
msig.egg-info/PKG-INFO
msig.egg-info/SOURCES.txt
msig.egg-info/dependency_links.txt
msig.egg-info/requires.txt
msig.egg-info/top_level.txt