Metadata-Version: 2.1
Name: msig
Version: 0.1.1
Summary: Statistical Significance Criteria for multivariate Time Series Motifs
Home-page: https://github.com/MiguelGarcaoSilva/msig
Author: Miguel G. Silva
Author-email: mmsilva@ciencias.ulisboa.pt
License: MIT
Keywords: time series motifs
Classifier: Development Status :: 3 - Alpha
Classifier: License :: OSI Approved :: MIT License
Classifier: Programming Language :: Python :: 3
License-File: LICENSE
Requires-Dist: numpy
Requires-Dist: scipy
